ugbio_cloud_utils/__init__.py
ugbio_cloud_utils/cloud_sync.py
ugbio_cloud_utils/file_handler_s3.py
ugbio_cloud_utils-1.20.0.dist-info/METADATA
ugbio_cloud_utils-1.20.0.dist-info/WHEEL
ugbio_cloud_utils-1.20.0.dist-info/entry_points.txt
ugbio_cloud_utils-1.20.0.dist-info/top_level.txt
ugbio_cloud_utils-1.20.0.dist-info/RECORD
