Metadata-Version: 2.4
Name: ugbio_cloud_utils
Version: 1.20.0
Summary: Ultima Genomics cloud python utils
Author-email: Avigail Moldovam  <avigail.moldovan@ultimagen.com>
Requires-Python: >=3.11
Requires-Dist: boto3>=1.35.66
Requires-Dist: google-cloud-storage>=2.19.0
Requires-Dist: pysam>=0.22.1
